voluta-0.3.0.dist-info/METADATA
voluta-0.3.0.dist-info/WHEEL
voluta/__init__.py
voluta/py.typed
voluta/voluta.cp310-win_amd64.pyd
voluta/voluta.pyi
voluta-0.3.0.dist-info/RECORD
