Metadata-Version: 2.4
Name: voluta
Version: 0.3.0
Classifier: Programming Language :: Rust
Classifier: Programming Language :: Python :: Implementation :: CPython
Classifier: License :: OSI Approved :: MIT License
Classifier: Topic :: Text Processing :: General
Requires-Dist: exceptiongroup>=1.2.2
Requires-Dist: maturin>=1.8.3
Summary: A high-performance text pattern matching library built with Rust
Author-email: "utils.rs" <dev@utils.rs>
License: MIT
Requires-Python: >=3.10
Project-URL: homepage, https://github.com/trustshield/voluta
Project-URL: changelog, https://github.com/trustshield/voluta/releases
Project-URL: issues, https://github.com/trustshield/voluta/issues
